geo_pysearch/__init__.py
geo_pysearch/cli.py
geo_pysearch/sdk.py
geo_pysearch/vector_search/__init__.py
geo_pysearch/vector_search/gpt_filter.py
geo_pysearch/vector_search/tiered_gpt_filter.py
geo_pysearch/vector_search/vector_search.py
geo_pysearch-0.1.7.dist-info/licenses/LICENSE
geo_pysearch-0.1.7.dist-info/METADATA
geo_pysearch-0.1.7.dist-info/WHEEL
geo_pysearch-0.1.7.dist-info/entry_points.txt
geo_pysearch-0.1.7.dist-info/top_level.txt
geo_pysearch-0.1.7.dist-info/RECORD
