Metadata-Version: 2.4
Name: geo_pysearch
Version: 0.1.7
Summary: GeoVectorSearch is a lightweight Python SDK and command-line tool for semantic discovery of GEO datasets suitable for differential gene expression analysis. Powered by FAISS-based vector search and optional GPT-based filtering, it helps researchers and developers quickly identify relevant RNA-seq or microarray datasets.
Author-email: Swapnonil Chakraborty <swapnonil0007@gmail.com>
License-Expression: GPL-3.0
Requires-Python: >=3.12
License-File: LICENSE
Requires-Dist: faiss-cpu>=1.11.0.post1
Requires-Dist: numpy>=2.3.2
Requires-Dist: pandas>=2.3.1
Requires-Dist: python-dotenv>=1.1.1
Requires-Dist: questionary>=2.1.0
Requires-Dist: sentence-transformers>=5.0.0
Requires-Dist: tenacity>=9.1.2
Requires-Dist: tqdm>=4.67.1
Dynamic: license-file
